TransCompR/TransCompR.py
TransCompR/__init__.py
TransCompR-0.1.dist-info/METADATA
TransCompR-0.1.dist-info/WHEEL
TransCompR-0.1.dist-info/top_level.txt
TransCompR-0.1.dist-info/RECORD
